{
    "영웅 약자 무시 각인서": {
        "Id": 65200103,
        "BundleCount": 1
    },
    "영웅 정기 흡수 각인서": {
        "Id": 65200203,
        "BundleCount": 1
    },
    "영웅 에테르 포식자 각인서": {
        "Id": 65200303,
        "BundleCount": 1
    },
    "영웅 안정된 상태 각인서": {
        "Id": 65200403,
        "BundleCount": 1
    },
    "영웅 원한 각인서": {
        "Id": 65200503,
        "BundleCount": 1
    },
    "영웅 굳은 의지 각인서": {
        "Id": 65200703,
        "BundleCount": 1
    },
    "영웅 구슬동자 각인서": {
        "Id": 65200803,
        "BundleCount": 1
    },
    "영웅 위기 모면 각인서": {
        "Id": 65200903,
        "BundleCount": 1
    },
    "영웅 예리한 둔기 각인서": {
        "Id": 65201003,
        "BundleCount": 1
    },
    "영웅 급소 타격 각인서": {
        "Id": 65201103,
        "BundleCount": 1
    },
    "영웅 최대 마나 증가 각인서": {
        "Id": 65201203,
        "BundleCount": 1
    },
    "영웅 마나 효율 증가 각인서": {
        "Id": 65201303,
        "BundleCount": 1
    },
    "영웅 탈출의 명수 각인서": {
        "Id": 65201403,
        "BundleCount": 1
    },
    "영웅 불굴 각인서": {
        "Id": 65201603,
        "BundleCount": 1
    },
    "영웅 분쇄의 주먹 각인서": {
        "Id": 65201703,
        "BundleCount": 1
    },
    "영웅 실드관통 각인서": {
        "Id": 65201803,
        "BundleCount": 1
    },
    "영웅 달인의 저력 각인서": {
        "Id": 65201903,
        "BundleCount": 1
    },
    "영웅 여신의 가호 각인서": {
        "Id": 65202003,
        "BundleCount": 1
    },
    "영웅 중갑 착용 각인서": {
        "Id": 65202103,
        "BundleCount": 1
    },
    "영웅 폭발물 전문가 각인서": {
        "Id": 65202203,
        "BundleCount": 1
    },
    "영웅 강화 방패 각인서": {
        "Id": 65202303,
        "BundleCount": 1
    },
    "영웅 강령술 각인서": {
        "Id": 65202403,
        "BundleCount": 1
    },
    "영웅 선수필승 각인서": {
        "Id": 65202503,
        "BundleCount": 1
    },
    "영웅 부러진 뼈 각인서": {
        "Id": 65202603,
        "BundleCount": 1
    },
    "영웅 번개의 분노 각인서": {
        "Id": 65202703,
        "BundleCount": 1
    },
    "영웅 저주받은 인형 각인서": {
        "Id": 65202803,
        "BundleCount": 1
    },
    "영웅 마나의 흐름 각인서": {
        "Id": 65203103,
        "BundleCount": 1
    },
    "영웅 바리케이드 각인서": {
        "Id": 65203203,
        "BundleCount": 1
    },
    "영웅 [홀리나이트] 심판자 각인서": {
        "Id": 65211413,
        "BundleCount": 1
    },
    "영웅 [바드] 진실된 용맹 각인서": {
        "Id": 65212313,
        "BundleCount": 1
    },
    "영웅 [바드] 절실한 구원 각인서": {
        "Id": 65212323,
        "BundleCount": 1
    },
    "영웅 [데모닉] 완벽한 억제 각인서": {
        "Id": 65214213,
        "BundleCount": 1
    },
    "영웅 [건슬링어] 피스메이커 각인서": {
        "Id": 65215613,
        "BundleCount": 1
    },
    "영웅 [건슬링어] 사냥의 시간 각인서": {
        "Id": 65215623,
        "BundleCount": 1
    },
    "영웅 [도화가] 회귀 각인서": {
        "Id": 65216113,
        "BundleCount": 1
    },
    "영웅 [도화가] 만개 각인서": {
        "Id": 65216123,
        "BundleCount": 1
    },
    "영웅 [기상술사] 질풍노도 각인서": {
        "Id": 65216213,
        "BundleCount": 1
    },
    "영웅 승부사 각인서": {
        "Id": 65202903,
        "BundleCount": 1
    },
    "영웅 돌격대장 각인서": {
        "Id": 65203303,
        "BundleCount": 1
    },
    "영웅 타격의 대가 각인서": {
        "Id": 65203703,
        "BundleCount": 1
    },
    "영웅 속전속결 각인서": {
        "Id": 65204003,
        "BundleCount": 1
    },
    "영웅 [홀리나이트] 축복의 오라 각인서": {
        "Id": 65211423,
        "BundleCount": 1
    },
    "영웅 [소서리스] 점화 각인서": {
        "Id": 65212413,
        "BundleCount": 1
    },
    "영웅 [소서리스] 환류 각인서": {
        "Id": 65212423,
        "BundleCount": 1
    },
    "영웅 [인파이터] 충격 단련 각인서": {
        "Id": 65213223,
        "BundleCount": 1
    },
    "영웅 [창술사] 절정 각인서": {
        "Id": 65213413,
        "BundleCount": 1
    },
    "영웅 [소울이터] 그믐의 경계 각인서": {
        "Id": 65214423,
        "BundleCount": 1
    },
    "영웅 [스카우터] 진화의 유산 각인서": {
        "Id": 65215423,
        "BundleCount": 1
    },
    "영웅 슈퍼 차지 각인서": {
        "Id": 65200603,
        "BundleCount": 1
    },
    "영웅 질량 증가 각인서": {
        "Id": 65203503,
        "BundleCount": 1
    },
    "영웅 [워로드] 고독한 기사 각인서": {
        "Id": 65211323,
        "BundleCount": 1
    },
    "영웅 [서머너] 상급 소환사 각인서": {
        "Id": 65212213,
        "BundleCount": 1
    },
    "영웅 [서머너] 넘치는 교감 각인서": {
        "Id": 65212223,
        "BundleCount": 1
    },
    "영웅 [창술사] 절제 각인서": {
        "Id": 65213423,
        "BundleCount": 1
    },
    "영웅 [데모닉] 멈출 수 없는 충동 각인서": {
        "Id": 65214223,
        "BundleCount": 1
    },
    "영웅 [호크아이] 두 번째 동료 각인서": {
        "Id": 65215113,
        "BundleCount": 1
    },
    "영웅 [호크아이] 죽음의 습격 각인서": {
        "Id": 65215123,
        "BundleCount": 1
    },
    "영웅 [스카우터] 아르데타인의 기술 각인서": {
        "Id": 65215413,
        "BundleCount": 1
    },
    "영웅 [기상술사] 이슬비 각인서": {
        "Id": 65216223,
        "BundleCount": 1
    },
    "영웅 정밀 단도 각인서": {
        "Id": 65204303,
        "BundleCount": 1
    },
    "영웅 [브레이커] 수라의 길 각인서": {
        "Id": 65213723,
        "BundleCount": 1
    },
    "영웅 결투의 대가 각인서": {
        "Id": 65201503,
        "BundleCount": 1
    },
    "영웅 기습의 대가 각인서": {
        "Id": 65203003,
        "BundleCount": 1
    },
    "영웅 아드레날린 각인서": {
        "Id": 65203903,
        "BundleCount": 1
    },
    "영웅 [슬레이어] 처단자 각인서": {
        "Id": 65211623,
        "BundleCount": 1
    },
    "영웅 [배틀마스터] 오의 강화 각인서": {
        "Id": 65213113,
        "BundleCount": 1
    },
    "영웅 [블레이드] 버스트 각인서": {
        "Id": 65214123,
        "BundleCount": 1
    },
    "영웅 [소울이터] 만월의 집행자 각인서": {
        "Id": 65214413,
        "BundleCount": 1
    },
    "영웅 [버서커] 광전사의 비기 각인서": {
        "Id": 65211123,
        "BundleCount": 1
    },
    "영웅 [디스트로이어] 중력 수련 각인서": {
        "Id": 65211223,
        "BundleCount": 1
    },
    "영웅 [배틀마스터] 초심 각인서": {
        "Id": 65213123,
        "BundleCount": 1
    },
    "영웅 [스트라이커] 오의난무 각인서": {
        "Id": 65213623,
        "BundleCount": 1
    },
    "영웅 [브레이커] 권왕파천무 각인서": {
        "Id": 65213713,
        "BundleCount": 1
    },
    "영웅 각성 각인서": {
        "Id": 65203403,
        "BundleCount": 1
    },
    "영웅 [아르카나] 황제의 칙령 각인서": {
        "Id": 65212123,
        "BundleCount": 1
    },
    "영웅 [블레이드] 잔재된 기운 각인서": {
        "Id": 65214113,
        "BundleCount": 1
    },
    "영웅 [데빌헌터] 핸드거너 각인서": {
        "Id": 65215223,
        "BundleCount": 1
    },
    "영웅 [블래스터] 포격 강화 각인서": {
        "Id": 65215323,
        "BundleCount": 1
    },
    "영웅 [아르카나] 황후의 은총 각인서": {
        "Id": 65212113,
        "BundleCount": 1
    },
    "영웅 시선 집중 각인서": {
        "Id": 65203803,
        "BundleCount": 1
    },
    "영웅 [기공사] 역천지체 각인서": {
        "Id": 65213323,
        "BundleCount": 1
    },
    "영웅 전문의 각인서": {
        "Id": 65204103,
        "BundleCount": 1
    },
    "영웅 [스트라이커] 일격필살 각인서": {
        "Id": 65213613,
        "BundleCount": 1
    },
    "영웅 [리퍼] 갈증 각인서": {
        "Id": 65214313,
        "BundleCount": 1
    },
    "영웅 [인파이터] 극의: 체술 각인서": {
        "Id": 65213213,
        "BundleCount": 1
    },
    "영웅 긴급구조 각인서": {
        "Id": 65204203,
        "BundleCount": 1
    },
    "영웅 [슬레이어] 포식자 각인서": {
        "Id": 65211613,
        "BundleCount": 1
    },
    "영웅 [블래스터] 화력 강화 각인서": {
        "Id": 65215313,
        "BundleCount": 1
    },
    "영웅 [리퍼] 달의 소리 각인서": {
        "Id": 65214323,
        "BundleCount": 1
    },
    "영웅 [디스트로이어] 분노의 망치 각인서": {
        "Id": 65211213,
        "BundleCount": 1
    },
    "영웅 [기공사] 세맥타통 각인서": {
        "Id": 65213313,
        "BundleCount": 1
    },
    "영웅 [데빌헌터] 강화 무기 각인서": {
        "Id": 65215213,
        "BundleCount": 1
    },
    "영웅 [버서커] 광기 각인서": {
        "Id": 65211113,
        "BundleCount": 1
    },
    "영웅 추진력 각인서": {
        "Id": 65203603,
        "BundleCount": 1
    },
    "영웅 [워로드] 전투 태세 각인서": {
        "Id": 65211313,
        "BundleCount": 1
    },
    "전설 굳은 의지 각인서": {
        "Id": 65200704,
        "BundleCount": 1
    },
    "전설 탈출의 명수 각인서": {
        "Id": 65201404,
        "BundleCount": 1
    },
    "전설 달인의 저력 각인서": {
        "Id": 65201904,
        "BundleCount": 1
    },
    "전설 여신의 가호 각인서": {
        "Id": 65202004,
        "BundleCount": 1
    },
    "전설 폭발물 전문가 각인서": {
        "Id": 65202204,
        "BundleCount": 1
    },
    "전설 강화 방패 각인서": {
        "Id": 65202304,
        "BundleCount": 1
    },
    "전설 분쇄의 주먹 각인서": {
        "Id": 65201704,
        "BundleCount": 1
    },
    "전설 부러진 뼈 각인서": {
        "Id": 65202604,
        "BundleCount": 1
    },
    "전설 [버서커] 광기 각인서": {
        "Id": 65211114,
        "BundleCount": 1
    },
    "전설 [바드] 진실된 용맹 각인서": {
        "Id": 65212314,
        "BundleCount": 1
    },
    "전설 실드관통 각인서": {
        "Id": 65201804,
        "BundleCount": 1
    },
    "전설 [스트라이커] 오의난무 각인서": {
        "Id": 65213624,
        "BundleCount": 1
    },
    "전설 [스카우터] 아르데타인의 기술 각인서": {
        "Id": 65215414,
        "BundleCount": 1
    },
    "전설 최대 마나 증가 각인서": {
        "Id": 65201204,
        "BundleCount": 1
    },
    "전설 불굴 각인서": {
        "Id": 65201604,
        "BundleCount": 1
    },
    "전설 [홀리나이트] 심판자 각인서": {
        "Id": 65211414,
        "BundleCount": 1
    },
    "전설 [아르카나] 황제의 칙령 각인서": {
        "Id": 65212124,
        "BundleCount": 1
    },
    "전설 [소서리스] 환류 각인서": {
        "Id": 65212424,
        "BundleCount": 1
    },
    "전설 [호크아이] 죽음의 습격 각인서": {
        "Id": 65215124,
        "BundleCount": 1
    },
    "전설 [블래스터] 화력 강화 각인서": {
        "Id": 65215314,
        "BundleCount": 1
    },
    "전설 [도화가] 회귀 각인서": {
        "Id": 65216114,
        "BundleCount": 1
    },
    "전설 [인파이터] 충격 단련 각인서": {
        "Id": 65213224,
        "BundleCount": 1
    },
    "전설 에테르 포식자 각인서": {
        "Id": 65200304,
        "BundleCount": 1
    },
    "전설 [스카우터] 진화의 유산 각인서": {
        "Id": 65215424,
        "BundleCount": 1
    },
    "전설 위기 모면 각인서": {
        "Id": 65200904,
        "BundleCount": 1
    },
    "전설 번개의 분노 각인서": {
        "Id": 65202704,
        "BundleCount": 1
    },
    "전설 [버서커] 광전사의 비기 각인서": {
        "Id": 65211124,
        "BundleCount": 1
    },
    "전설 [워로드] 전투 태세 각인서": {
        "Id": 65211314,
        "BundleCount": 1
    },
    "전설 [기공사] 세맥타통 각인서": {
        "Id": 65213314,
        "BundleCount": 1
    },
    "전설 [호크아이] 두 번째 동료 각인서": {
        "Id": 65215114,
        "BundleCount": 1
    },
    "전설 [건슬링어] 사냥의 시간 각인서": {
        "Id": 65215624,
        "BundleCount": 1
    },
    "전설 [스트라이커] 일격필살 각인서": {
        "Id": 65213614,
        "BundleCount": 1
    },
    "전설 [데모닉] 완벽한 억제 각인서": {
        "Id": 65214214,
        "BundleCount": 1
    },
    "전설 [리퍼] 달의 소리 각인서": {
        "Id": 65214324,
        "BundleCount": 1
    },
    "전설 추진력 각인서": {
        "Id": 65203604,
        "BundleCount": 1
    },
    "전설 [서머너] 넘치는 교감 각인서": {
        "Id": 65212224,
        "BundleCount": 1
    },
    "전설 [창술사] 절제 각인서": {
        "Id": 65213424,
        "BundleCount": 1
    },
    "전설 [기공사] 역천지체 각인서": {
        "Id": 65213324,
        "BundleCount": 1
    },
    "전설 바리케이드 각인서": {
        "Id": 65203204,
        "BundleCount": 1
    },
    "전설 [디스트로이어] 중력 수련 각인서": {
        "Id": 65211224,
        "BundleCount": 1
    },
    "전설 [배틀마스터] 오의 강화 각인서": {
        "Id": 65213114,
        "BundleCount": 1
    },
    "전설 시선 집중 각인서": {
        "Id": 65203804,
        "BundleCount": 1
    },
    "전설 [데빌헌터] 핸드거너 각인서": {
        "Id": 65215224,
        "BundleCount": 1
    },
    "전설 [디스트로이어] 분노의 망치 각인서": {
        "Id": 65211214,
        "BundleCount": 1
    },
    "전설 승부사 각인서": {
        "Id": 65202904,
        "BundleCount": 1
    },
    "전설 [기상술사] 이슬비 각인서": {
        "Id": 65216224,
        "BundleCount": 1
    },
    "전설 [데빌헌터] 강화 무기 각인서": {
        "Id": 65215214,
        "BundleCount": 1
    },
    "전설 [창술사] 절정 각인서": {
        "Id": 65213414,
        "BundleCount": 1
    },
    "전설 급소 타격 각인서": {
        "Id": 65201104,
        "BundleCount": 1
    },
    "전설 [아르카나] 황후의 은총 각인서": {
        "Id": 65212114,
        "BundleCount": 1
    },
    "전설 [블래스터] 포격 강화 각인서": {
        "Id": 65215324,
        "BundleCount": 1
    },
    "전설 [슬레이어] 처단자 각인서": {
        "Id": 65211624,
        "BundleCount": 1
    },
    "전설 구슬동자 각인서": {
        "Id": 65200804,
        "BundleCount": 1
    },
    "전설 [서머너] 상급 소환사 각인서": {
        "Id": 65212214,
        "BundleCount": 1
    },
    "전설 약자 무시 각인서": {
        "Id": 65200104,
        "BundleCount": 1
    },
    "전설 [건슬링어] 피스메이커 각인서": {
        "Id": 65215614,
        "BundleCount": 1
    },
    "전설 마나 효율 증가 각인서": {
        "Id": 65201304,
        "BundleCount": 1
    },
    "전설 선수필승 각인서": {
        "Id": 65202504,
        "BundleCount": 1
    },
    "전설 [블레이드] 버스트 각인서": {
        "Id": 65214124,
        "BundleCount": 1
    },
    "전설 [홀리나이트] 축복의 오라 각인서": {
        "Id": 65211424,
        "BundleCount": 1
    },
    "전설 [배틀마스터] 초심 각인서": {
        "Id": 65213124,
        "BundleCount": 1
    },
    "전설 [워로드] 고독한 기사 각인서": {
        "Id": 65211324,
        "BundleCount": 1
    },
    "전설 강령술 각인서": {
        "Id": 65202404,
        "BundleCount": 1
    },
    "전설 [소서리스] 점화 각인서": {
        "Id": 65212414,
        "BundleCount": 1
    },
    "전설 [인파이터] 극의: 체술 각인서": {
        "Id": 65213214,
        "BundleCount": 1
    },
    "전설 [데모닉] 멈출 수 없는 충동 각인서": {
        "Id": 65214224,
        "BundleCount": 1
    },
    "전설 정밀 단도 각인서": {
        "Id": 65204304,
        "BundleCount": 1
    },
    "전설 [소울이터] 그믐의 경계 각인서": {
        "Id": 65214424,
        "BundleCount": 1
    },
    "전설 [바드] 절실한 구원 각인서": {
        "Id": 65212324,
        "BundleCount": 1
    },
    "전설 마나의 흐름 각인서": {
        "Id": 65203104,
        "BundleCount": 1
    },
    "전설 안정된 상태 각인서": {
        "Id": 65200404,
        "BundleCount": 1
    },
    "전설 긴급구조 각인서": {
        "Id": 65204204,
        "BundleCount": 1
    },
    "전설 [리퍼] 갈증 각인서": {
        "Id": 65214314,
        "BundleCount": 1
    },
    "전설 중갑 착용 각인서": {
        "Id": 65202104,
        "BundleCount": 1
    },
    "전설 속전속결 각인서": {
        "Id": 65204004,
        "BundleCount": 1
    },
    "전설 [도화가] 만개 각인서": {
        "Id": 65216124,
        "BundleCount": 1
    },
    "전설 [기상술사] 질풍노도 각인서": {
        "Id": 65216214,
        "BundleCount": 1
    },
    "전설 [슬레이어] 포식자 각인서": {
        "Id": 65211614,
        "BundleCount": 1
    },
    "전설 [브레이커] 권왕파천무 각인서": {
        "Id": 65213714,
        "BundleCount": 1
    },
    "전설 정기 흡수 각인서": {
        "Id": 65200204,
        "BundleCount": 1
    },
    "전설 [소울이터] 만월의 집행자 각인서": {
        "Id": 65214414,
        "BundleCount": 1
    },
    "전설 저주받은 인형 각인서": {
        "Id": 65202804,
        "BundleCount": 1
    },
    "전설 [블레이드] 잔재된 기운 각인서": {
        "Id": 65214114,
        "BundleCount": 1
    },
    "전설 결투의 대가 각인서": {
        "Id": 65201504,
        "BundleCount": 1
    },
    "전설 [브레이커] 수라의 길 각인서": {
        "Id": 65213724,
        "BundleCount": 1
    },
    "전설 슈퍼 차지 각인서": {
        "Id": 65200604,
        "BundleCount": 1
    },
    "전설 원한 각인서": {
        "Id": 65200504,
        "BundleCount": 1
    },
    "전설 전문의 각인서": {
        "Id": 65204104,
        "BundleCount": 1
    },
    "전설 각성 각인서": {
        "Id": 65203404,
        "BundleCount": 1
    },
    "전설 타격의 대가 각인서": {
        "Id": 65203704,
        "BundleCount": 1
    },
    "전설 질량 증가 각인서": {
        "Id": 65203504,
        "BundleCount": 1
    },
    "전설 예리한 둔기 각인서": {
        "Id": 65201004,
        "BundleCount": 1
    },
    "전설 돌격대장 각인서": {
        "Id": 65203304,
        "BundleCount": 1
    },
    "전설 기습의 대가 각인서": {
        "Id": 65203004,
        "BundleCount": 1
    },
    "전설 아드레날린 각인서": {
        "Id": 65203904,
        "BundleCount": 1
    },
    "유물 굳은 의지 각인서": {
        "Id": 65200705,
        "BundleCount": 1
    },
    "유물 긴급구조 각인서": {
        "Id": 65204205,
        "BundleCount": 1
    },
    "유물 분쇄의 주먹 각인서": {
        "Id": 65201705,
        "BundleCount": 1
    },
    "유물 탈출의 명수 각인서": {
        "Id": 65201405,
        "BundleCount": 1
    },
    "유물 강화 방패 각인서": {
        "Id": 65202305,
        "BundleCount": 1
    },
    "유물 강령술 각인서": {
        "Id": 65202405,
        "BundleCount": 1
    },
    "유물 여신의 가호 각인서": {
        "Id": 65202005,
        "BundleCount": 1
    },
    "유물 위기 모면 각인서": {
        "Id": 65200905,
        "BundleCount": 1
    },
    "유물 번개의 분노 각인서": {
        "Id": 65202705,
        "BundleCount": 1
    },
    "유물 불굴 각인서": {
        "Id": 65201605,
        "BundleCount": 1
    },
    "유물 부러진 뼈 각인서": {
        "Id": 65202605,
        "BundleCount": 1
    },
    "유물 실드관통 각인서": {
        "Id": 65201805,
        "BundleCount": 1
    },
    "유물 약자 무시 각인서": {
        "Id": 65200105,
        "BundleCount": 1
    },
    "유물 추진력 각인서": {
        "Id": 65203605,
        "BundleCount": 1
    },
    "유물 승부사 각인서": {
        "Id": 65202905,
        "BundleCount": 1
    },
    "유물 선수필승 각인서": {
        "Id": 65202505,
        "BundleCount": 1
    },
    "유물 달인의 저력 각인서": {
        "Id": 65201905,
        "BundleCount": 1
    },
    "유물 폭발물 전문가 각인서": {
        "Id": 65202205,
        "BundleCount": 1
    },
    "유물 시선 집중 각인서": {
        "Id": 65203805,
        "BundleCount": 1
    },
    "유물 정기 흡수 각인서": {
        "Id": 65200205,
        "BundleCount": 1
    },
    "유물 최대 마나 증가 각인서": {
        "Id": 65201205,
        "BundleCount": 1
    },
    "유물 에테르 포식자 각인서": {
        "Id": 65200305,
        "BundleCount": 1
    },
    "유물 급소 타격 각인서": {
        "Id": 65201105,
        "BundleCount": 1
    },
    "유물 중갑 착용 각인서": {
        "Id": 65202105,
        "BundleCount": 1
    },
    "유물 정밀 단도 각인서": {
        "Id": 65204305,
        "BundleCount": 1
    },
    "유물 각성 각인서": {
        "Id": 65203405,
        "BundleCount": 1
    },
    "유물 마나 효율 증가 각인서": {
        "Id": 65201305,
        "BundleCount": 1
    },
    "유물 안정된 상태 각인서": {
        "Id": 65200405,
        "BundleCount": 1
    },
    "유물 바리케이드 각인서": {
        "Id": 65203205,
        "BundleCount": 1
    },
    "유물 구슬동자 각인서": {
        "Id": 65200805,
        "BundleCount": 1
    },
    "유물 속전속결 각인서": {
        "Id": 65204005,
        "BundleCount": 1
    },
    "유물 전문의 각인서": {
        "Id": 65204105,
        "BundleCount": 1
    },
    "유물 결투의 대가 각인서": {
        "Id": 65201505,
        "BundleCount": 1
    },
    "유물 슈퍼 차지 각인서": {
        "Id": 65200605,
        "BundleCount": 1
    },
    "유물 마나의 흐름 각인서": {
        "Id": 65203105,
        "BundleCount": 1
    },
    "유물 질량 증가 각인서": {
        "Id": 65203505,
        "BundleCount": 1
    },
    "유물 타격의 대가 각인서": {
        "Id": 65203705,
        "BundleCount": 1
    },
    "유물 기습의 대가 각인서": {
        "Id": 65203005,
        "BundleCount": 1
    },
    "유물 저주받은 인형 각인서": {
        "Id": 65202805,
        "BundleCount": 1
    },
    "유물 돌격대장 각인서": {
        "Id": 65203305,
        "BundleCount": 1
    },
    "유물 예리한 둔기 각인서": {
        "Id": 65201005,
        "BundleCount": 1
    },
    "유물 원한 각인서": {
        "Id": 65200505,
        "BundleCount": 1
    },
    "유물 아드레날린 각인서": {
        "Id": 65203905,
        "BundleCount": 1
    },
    "일반 파괴석 조각 [10개 단위 판매]": {
        "Id": 66102001,
        "BundleCount": 10
    },
    "일반 파괴석 결정 [10개 단위 판매]": {
        "Id": 66102003,
        "BundleCount": 10
    },
    "일반 수호석 조각 [10개 단위 판매]": {
        "Id": 66102101,
        "BundleCount": 10
    },
    "일반 수호석 결정 [10개 단위 판매]": {
        "Id": 66102103,
        "BundleCount": 10
    },
    "일반 수호강석 [10개 단위 판매]": {
        "Id": 66102104,
        "BundleCount": 10
    },
    "일반 파괴석 [10개 단위 판매]": {
        "Id": 66102002,
        "BundleCount": 10
    },
    "일반 파괴강석 [10개 단위 판매]": {
        "Id": 66102004,
        "BundleCount": 10
    },
    "일반 수호석 [10개 단위 판매]": {
        "Id": 66102102,
        "BundleCount": 10
    },
    "일반 정제된 수호강석 [10개 단위 판매]": {
        "Id": 66102105,
        "BundleCount": 10
    },
    "일반 운명의 수호석 [10개 단위 판매]": {
        "Id": 66102106,
        "BundleCount": 10
    },
    "일반 정제된 파괴강석 [10개 단위 판매]": {
        "Id": 66102005,
        "BundleCount": 10
    },
    "일반 운명의 파괴석 [10개 단위 판매]": {
        "Id": 66102006,
        "BundleCount": 10
    },
    "고급 태양의 은총": {
        "Id": 66111121,
        "BundleCount": 1
    },
    "고급 운명의 파편 주머니(소)": {
        "Id": 66130141,
        "BundleCount": 1
    },
    "고급 명예의 파편 주머니(소)": {
        "Id": 66130131,
        "BundleCount": 1
    },
    "고급 조화의 파편 주머니(소)": {
        "Id": 66130121,
        "BundleCount": 1
    },
    "희귀 조화의 돌파석": {
        "Id": 66110204,
        "BundleCount": 1
    },
    "희귀 명예의 돌파석": {
        "Id": 66110221,
        "BundleCount": 1
    },
    "희귀 위대한 명예의 돌파석": {
        "Id": 66110222,
        "BundleCount": 1
    },
    "희귀 경이로운 명예의 돌파석": {
        "Id": 66110223,
        "BundleCount": 1
    },
    "희귀 생명의 돌파석": {
        "Id": 66110214,
        "BundleCount": 1
    },
    "희귀 오레하 융화 재료": {
        "Id": 6861008,
        "BundleCount": 1
    },
    "희귀 운명의 돌파석": {
        "Id": 66110225,
        "BundleCount": 1
    },
    "희귀 찬란한 명예의 돌파석": {
        "Id": 66110224,
        "BundleCount": 1
    },
    "희귀 태양의 축복": {
        "Id": 66111122,
        "BundleCount": 1
    },
    "희귀 아비도스 융화 재료": {
        "Id": 6861012,
        "BundleCount": 1
    },
    "희귀 운명의 파편 주머니(중)": {
        "Id": 66130142,
        "BundleCount": 1
    },
    "희귀 아크투르스의 서 : 방어구": {
        "Id": 66112214,
        "BundleCount": 1
    },
    "희귀 명예의 파편 주머니(중)": {
        "Id": 66130132,
        "BundleCount": 1
    },
    "희귀 조화의 파편 주머니(중)": {
        "Id": 66130122,
        "BundleCount": 1
    },
    "영웅 별의 숨결": {
        "Id": 66111104,
        "BundleCount": 1
    },
    "영웅 선명한 지혜의 정수": {
        "Id": 66160220,
        "BundleCount": 1
    },
    "영웅 달의 숨결": {
        "Id": 66111114,
        "BundleCount": 1
    },
    "영웅 상급 오레하 융화 재료": {
        "Id": 6861009,
        "BundleCount": 1
    },
    "영웅 재봉술 : 비늘 [5-7]": {
        "Id": 66112524,
        "BundleCount": 1
    },
    "영웅 야금술 : 비늘 [5-7]": {
        "Id": 66112521,
        "BundleCount": 1
    },
    "영웅 재봉술 : 매듭 기본": {
        "Id": 66112514,
        "BundleCount": 1
    },
    "영웅 야금술 : 접쇠 기본": {
        "Id": 66112511,
        "BundleCount": 1
    },
    "영웅 최상급 오레하 융화 재료": {
        "Id": 6861011,
        "BundleCount": 1
    },
    "영웅 현자의 가루": {
        "Id": 66141103,
        "BundleCount": 1
    },
    "영웅 태양의 가호": {
        "Id": 66111123,
        "BundleCount": 1
    },
    "영웅 빙하의 숨결": {
        "Id": 66111132,
        "BundleCount": 1
    },
    "영웅 크라테르의 지혜 : 방어구": {
        "Id": 66112205,
        "BundleCount": 1
    },
    "영웅 야금술 : 주조 기본": {
        "Id": 66112501,
        "BundleCount": 1
    },
    "영웅 아크투르스의 의지 : 방어구": {
        "Id": 66112215,
        "BundleCount": 1
    },
    "영웅 명예의 파편 주머니(대)": {
        "Id": 66130133,
        "BundleCount": 1
    },
    "영웅 용암의 숨결": {
        "Id": 66111131,
        "BundleCount": 1
    },
    "영웅 아크투르스의 의지 : 무기": {
        "Id": 66112212,
        "BundleCount": 1
    },
    "영웅 크라테르의 지혜 : 무기": {
        "Id": 66112202,
        "BundleCount": 1
    },
    "영웅 조화의 파편 주머니(대)": {
        "Id": 66130123,
        "BundleCount": 1
    },
    "전설 야금술 : 선혈 [8-10]": {
        "Id": 66112522,
        "BundleCount": 1
    },
    "전설 재봉술 : 선혈 [8-10]": {
        "Id": 66112525,
        "BundleCount": 1
    },
    "전설 마력석 조각": {
        "Id": 66172060,
        "BundleCount": 1
    },
    "전설 빛나는 지혜의 정수": {
        "Id": 66160320,
        "BundleCount": 1
    },
    "전설 크라테르의 권능 : 방어구": {
        "Id": 66112206,
        "BundleCount": 1
    },
    "유물 재봉술 : 마수 [11-15]": {
        "Id": 66112526,
        "BundleCount": 1
    },
    "유물 재봉술 : 몽환 [13-15]": {
        "Id": 66112534,
        "BundleCount": 1
    },
    "유물 야금술 : 마수 [11-15]": {
        "Id": 66112523,
        "BundleCount": 1
    },
    "유물 야금술 : 몽환 [13-15]": {
        "Id": 66112531,
        "BundleCount": 1
    },
    "유물 재봉술 : 업화 [11-14]": {
        "Id": 66112546,
        "BundleCount": 1
    },
    "유물 야금술 : 업화 [11-14]": {
        "Id": 66112543,
        "BundleCount": 1
    },
    "유물 재봉술 : 매듭 심화": {
        "Id": 66112516,
        "BundleCount": 1
    },
    "고대 야금술 : 쇠락 [16-19]": {
        "Id": 66112542,
        "BundleCount": 1
    },
    "고대 야금술 : 몽환 [16-19]": {
        "Id": 66112532,
        "BundleCount": 1
    },
    "고대 재봉술 : 쇠락 [16-19]": {
        "Id": 66112545,
        "BundleCount": 1
    },
    "고대 재봉술 : 몽환 [16-19]": {
        "Id": 66112535,
        "BundleCount": 1
    },
    "고대 야금술 : 쇠락 [13-15]": {
        "Id": 66112541,
        "BundleCount": 1
    },
    "고대 재봉술 : 쇠락 [13-15]": {
        "Id": 66112544,
        "BundleCount": 1
    },
    "에스더 에스더의 기운": {
        "Id": 66150010,
        "BundleCount": 1
    },
    "고급 회복약": {
        "Id": 101061,
        "BundleCount": 1
    },
    "고급 신호탄": {
        "Id": 101042,
        "BundleCount": 1
    },
    "고급 빛나는 신호탄": {
        "Id": 101935,
        "BundleCount": 1
    },
    "희귀 섬광 수류탄": {
        "Id": 101001,
        "BundleCount": 1
    },
    "희귀 보호 물약": {
        "Id": 101181,
        "BundleCount": 1
    },
    "희귀 전기 수류탄": {
        "Id": 101031,
        "BundleCount": 1
    },
    "희귀 위장 로브": {
        "Id": 101122,
        "BundleCount": 1
    },
    "희귀 페로몬 정수": {
        "Id": 101916,
        "BundleCount": 1
    },
    "희귀 냉기 수류탄": {
        "Id": 101021,
        "BundleCount": 1
    },
    "희귀 모닥불": {
        "Id": 101081,
        "BundleCount": 1
    },
    "희귀 정비소 이동 포탈 주문서": {
        "Id": 101914,
        "BundleCount": 1
    },
    "희귀 도발 허수아비": {
        "Id": 101052,
        "BundleCount": 1
    },
    "희귀 만능 물약": {
        "Id": 101015,
        "BundleCount": 1
    },
    "희귀 고급 회복약": {
        "Id": 101062,
        "BundleCount": 1
    },
    "희귀 빛나는 천둥 물약": {
        "Id": 101931,
        "BundleCount": 1
    },
    "희귀 빛나는 위장 로브": {
        "Id": 101932,
        "BundleCount": 1
    },
    "희귀 점토 수류탄": {
        "Id": 101231,
        "BundleCount": 1
    },
    "희귀 암흑 수류탄": {
        "Id": 101151,
        "BundleCount": 1
    },
    "희귀 회오리 수류탄": {
        "Id": 101221,
        "BundleCount": 1
    },
    "희귀 성스러운 폭탄": {
        "Id": 101271,
        "BundleCount": 1
    },
    "희귀 빛나는 보호 물약": {
        "Id": 101930,
        "BundleCount": 1
    },
    "희귀 신속 로브": {
        "Id": 101211,
        "BundleCount": 1
    },
    "희귀 빛나는 전기 수류탄": {
        "Id": 101921,
        "BundleCount": 1
    },
    "희귀 화염 수류탄": {
        "Id": 101011,
        "BundleCount": 1
    },
    "희귀 성스러운 부적": {
        "Id": 101191,
        "BundleCount": 1
    },
    "희귀 진군의 깃발": {
        "Id": 101101,
        "BundleCount": 1
    },
    "희귀 파괴 폭탄": {
        "Id": 101912,
        "BundleCount": 1
    },
    "희귀 수면 폭탄": {
        "Id": 101261,
        "BundleCount": 1
    },
    "희귀 부식 폭탄": {
        "Id": 101171,
        "BundleCount": 1
    },
    "희귀 빛나는 도발 허수아비": {
        "Id": 101937,
        "BundleCount": 1
    },
    "희귀 빛나는 만능 물약": {
        "Id": 101929,
        "BundleCount": 1
    },
    "희귀 빛나는 신속 로브": {
        "Id": 101934,
        "BundleCount": 1
    },
    "희귀 빛나는 냉기 수류탄": {
        "Id": 101920,
        "BundleCount": 1
    },
    "희귀 빛나는 섬광 수류탄": {
        "Id": 101918,
        "BundleCount": 1
    },
    "희귀 천둥 물약": {
        "Id": 101203,
        "BundleCount": 1
    },
    "희귀 빛나는 화염 수류탄": {
        "Id": 101919,
        "BundleCount": 1
    },
    "희귀 빛나는 점토 수류탄": {
        "Id": 101922,
        "BundleCount": 1
    },
    "희귀 빛나는 회오리 수류탄": {
        "Id": 101923,
        "BundleCount": 1
    },
    "희귀 빛나는 파괴 폭탄": {
        "Id": 101926,
        "BundleCount": 1
    },
    "희귀 빛나는 모닥불": {
        "Id": 101936,
        "BundleCount": 1
    },
    "희귀 빛나는 암흑 수류탄": {
        "Id": 101924,
        "BundleCount": 1
    },
    "희귀 불꽃 마법 스크롤": {
        "Id": 101940,
        "BundleCount": 1
    },
    "희귀 빛나는 성스러운 폭탄": {
        "Id": 101928,
        "BundleCount": 1
    },
    "희귀 빛나는 수면 폭탄": {
        "Id": 101925,
        "BundleCount": 1
    },
    "희귀 빛나는 부식 폭탄": {
        "Id": 101927,
        "BundleCount": 1
    },
    "희귀 빛나는 진군의 깃발": {
        "Id": 101939,
        "BundleCount": 1
    },
    "희귀 빛나는 성스러운 부적": {
        "Id": 101938,
        "BundleCount": 1
    },
    "영웅 시간 정지 물약": {
        "Id": 101915,
        "BundleCount": 1
    },
    "영웅 은신 로브": {
        "Id": 101131,
        "BundleCount": 1
    },
    "영웅 빛나는 은신 로브": {
        "Id": 101933,
        "BundleCount": 1
    },
    "영웅 각성 물약": {
        "Id": 101072,
        "BundleCount": 1
    },
    "영웅 정령의 회복약": {
        "Id": 101063,
        "BundleCount": 1
    },
    "영웅 아드로핀 물약": {
        "Id": 101291,
        "BundleCount": 1
    },
    "영웅 루테란의 나팔": {
        "Id": 101301,
        "BundleCount": 1
    },
    "영웅 빛나는 정령의 회복약": {
        "Id": 101917,
        "BundleCount": 1
    },
    "고급 [일품] 장인의 스튜": {
        "Id": 6851101,
        "BundleCount": 1
    },
    "고급 [일품] 장인의 오믈렛": {
        "Id": 6851201,
        "BundleCount": 1
    },
    "고급 [일품] 장인의 꼬치구이": {
        "Id": 6851301,
        "BundleCount": 1
    },
    "고급 [일품] 장인의 스테이크": {
        "Id": 6851401,
        "BundleCount": 1
    },
    "고급 [일품] 장인의 폭신한 오믈렛 [10개 단위 판매]": {
        "Id": 6854003,
        "BundleCount": 10
    },
    "고급 [일품] 장인의 노릇한 꼬치구이 [10개 단위 판매]": {
        "Id": 6854001,
        "BundleCount": 10
    },
    "고급 [일품] 장인의 매콤한 스튜 [10개 단위 판매]": {
        "Id": 6854002,
        "BundleCount": 10
    },
    "고급 [일품] 명인의 촉촉한 오믈렛 [10개 단위 판매]": {
        "Id": 6854011,
        "BundleCount": 10
    },
    "고급 [일품] 명인의 쫄깃한 꼬치구이 [10개 단위 판매]": {
        "Id": 6854009,
        "BundleCount": 10
    },
    "고급 [일품] 달인의 바삭한 꼬치구이 [10개 단위 판매]": {
        "Id": 6854005,
        "BundleCount": 10
    },
    "고급 [일품] 명인의 짭짤한 스튜 [10개 단위 판매]": {
        "Id": 6854010,
        "BundleCount": 10
    },
    "고급 [일품] 달인의 달콤한 스튜 [10개 단위 판매]": {
        "Id": 6854006,
        "BundleCount": 10
    },
    "고급 [일품] 달인의 부드러운 오믈렛 [10개 단위 판매]": {
        "Id": 6854007,
        "BundleCount": 10
    },
    "고급 [일품] 대가의 전통 오믈렛 [10개 단위 판매]": {
        "Id": 6854015,
        "BundleCount": 10
    },
    "고급 [일품] 대가의 양념 꼬치구이 [10개 단위 판매]": {
        "Id": 6854013,
        "BundleCount": 10
    },
    "고급 [일품] 대가의 모둠 스튜 [10개 단위 판매]": {
        "Id": 6854014,
        "BundleCount": 10
    },
    "고급 [일품] 거장의 비프 오믈렛 [10개 단위 판매]": {
        "Id": 6854019,
        "BundleCount": 10
    },
    "고급 [일품] 거장의 수제 꼬치구이 [10개 단위 판매]": {
        "Id": 6854017,
        "BundleCount": 10
    },
    "고급 [일품] 거장의 특제 스튜 [10개 단위 판매]": {
        "Id": 6854018,
        "BundleCount": 10
    },
    "고급 [일품] 장인의 스테이크 정식": {
        "Id": 6851405,
        "BundleCount": 1
    },
    "고급 [일품] 달인의 스테이크": {
        "Id": 6851409,
        "BundleCount": 1
    },
    "고급 [일품] 달인의 오믈렛": {
        "Id": 6851209,
        "BundleCount": 1
    },
    "고급 [일품] 달인의 꼬치구이": {
        "Id": 6851309,
        "BundleCount": 1
    },
    "고급 [일품] 달인의 전통 오믈렛": {
        "Id": 6851213,
        "BundleCount": 1
    },
    "고급 [일품] 달인의 스튜": {
        "Id": 6851109,
        "BundleCount": 1
    },
    "고급 [일품] 달인의 스테이크 정식": {
        "Id": 6851413,
        "BundleCount": 1
    },
    "고급 [일품] 달인의 모둠 스튜": {
        "Id": 6851113,
        "BundleCount": 1
    },
    "고급 [일품] 명인의 스튜": {
        "Id": 6851117,
        "BundleCount": 1
    },
    "고급 [일품] 명인의 오믈렛": {
        "Id": 6851217,
        "BundleCount": 1
    },
    "고급 [일품] 달인의 양념 꼬치구이": {
        "Id": 6851313,
        "BundleCount": 1
    },
    "고급 [일품] 명인의 스테이크": {
        "Id": 6851417,
        "BundleCount": 1
    },
    "희귀 스윌렛 볼로네제 V": {
        "Id": 821035,
        "BundleCount": 1
    },
    "희귀 별구름 카프레제 V": {
        "Id": 821005,
        "BundleCount": 1
    },
    "희귀 별구름 카프레제 IV": {
        "Id": 821004,
        "BundleCount": 1
    },
    "희귀 스윌렛 볼로네제 IV": {
        "Id": 821034,
        "BundleCount": 1
    },
    "희귀 스윌렛 볼로네제 VI": {
        "Id": 821036,
        "BundleCount": 1
    },
    "희귀 아일렛 비스테카 V": {
        "Id": 821045,
        "BundleCount": 1
    },
    "희귀 꿈결바람 케이크 V": {
        "Id": 821015,
        "BundleCount": 1
    },
    "희귀 [일품] 장인의 매콤한 스튜": {
        "Id": 6851102,
        "BundleCount": 1
    },
    "희귀 아일렛 비스테카 VI": {
        "Id": 821046,
        "BundleCount": 1
    },
    "희귀 [일품] 명인의 달콤한 스튜": {
        "Id": 6851119,
        "BundleCount": 1
    },
    "희귀 [일품] 장인의 마늘 스테이크 정식 [10개 단위 판매]": {
        "Id": 6854004,
        "BundleCount": 10
    },
    "희귀 [일품] 장인의 버터 스테이크 정식": {
        "Id": 6851407,
        "BundleCount": 1
    },
    "희귀 [일품] 장인의 촉촉한 오믈렛": {
        "Id": 6851204,
        "BundleCount": 1
    },
    "희귀 [일품] 장인의 짭짤한 스튜": {
        "Id": 6851104,
        "BundleCount": 1
    },
    "희귀 꿈결바람 케이크 IV": {
        "Id": 821014,
        "BundleCount": 1
    },
    "희귀 [일품] 명인의 마늘 스테이크": {
        "Id": 6851418,
        "BundleCount": 1
    },
    "희귀 [일품] 명인의 폭신한 오믈렛": {
        "Id": 6851218,
        "BundleCount": 1
    },
    "희귀 그릴피쉬 피카타 V": {
        "Id": 821055,
        "BundleCount": 1
    },
    "희귀 [일품] 명인의 허브 스테이크 정식 [10개 단위 판매]": {
        "Id": 6854012,
        "BundleCount": 10
    },
    "희귀 [일품] 달인의 버터 스테이크 정식 [10개 단위 판매]": {
        "Id": 6854008,
        "BundleCount": 10
    },
    "희귀 꿈결바람 케이크 VI": {
        "Id": 821016,
        "BundleCount": 1
    },
    "희귀 [일품] 명인의 매콤한 스튜": {
        "Id": 6851118,
        "BundleCount": 1
    },
    "희귀 [일품] 대가의 안심 스테이크 정식 [10개 단위 판매]": {
        "Id": 6854016,
        "BundleCount": 10
    },
    "희귀 [일품] 달인의 폭신한 오믈렛": {
        "Id": 6851210,
        "BundleCount": 1
    },
    "희귀 [일품] 달인의 촉촉한 전통 오믈렛": {
        "Id": 6851216,
        "BundleCount": 1
    },
    "희귀 [일품] 장인의 부드러운 오믈렛": {
        "Id": 6851203,
        "BundleCount": 1
    },
    "희귀 [일품] 거장의 채끝 스테이크 정식 [10개 단위 판매]": {
        "Id": 6854020,
        "BundleCount": 10
    },
    "희귀 [일품] 장인의 촉촉한 전통 오믈렛": {
        "Id": 6851208,
        "BundleCount": 1
    },
    "희귀 [일품] 장인의 폭신한 전통 오믈렛": {
        "Id": 6851206,
        "BundleCount": 1
    },
    "희귀 [일품] 장인의 부드러운 전통 오믈렛": {
        "Id": 6851207,
        "BundleCount": 1
    },
    "희귀 아일렛 비스테카 IV": {
        "Id": 821044,
        "BundleCount": 1
    },
    "희귀 [일품] 장인의 마늘 스테이크": {
        "Id": 6851402,
        "BundleCount": 1
    },
    "희귀 [일품] 장인의 버터 스테이크": {
        "Id": 6851403,
        "BundleCount": 1
    },
    "희귀 [일품] 장인의 마늘 스테이크 정식": {
        "Id": 6851406,
        "BundleCount": 1
    },
    "희귀 [일품] 달인의 짭짤한 스튜": {
        "Id": 6851112,
        "BundleCount": 1
    },
    "희귀 [일품] 장인의 폭신한 오믈렛": {
        "Id": 6851202,
        "BundleCount": 1
    },
    "희귀 별구름 카프레제 II": {
        "Id": 821002,
        "BundleCount": 1
    },
    "희귀 별구름 카프레제 III": {
        "Id": 821003,
        "BundleCount": 1
    },
    "희귀 스윌렛 볼로네제 II": {
        "Id": 821032,
        "BundleCount": 1
    },
    "희귀 [일품] 장인의 달콤한 스튜": {
        "Id": 6851103,
        "BundleCount": 1
    },
    "희귀 [일품] 장인의 허브 스테이크": {
        "Id": 6851404,
        "BundleCount": 1
    },
    "희귀 [일품] 장인의 허브 스테이크 정식": {
        "Id": 6851408,
        "BundleCount": 1
    },
    "희귀 [일품] 달인의 버터 스테이크": {
        "Id": 6851411,
        "BundleCount": 1
    },
    "희귀 [일품] 명인의 바삭한 꼬치구이": {
        "Id": 6851319,
        "BundleCount": 1
    },
    "희귀 [일품] 장인의 달콤한 모둠 스튜": {
        "Id": 6851107,
        "BundleCount": 1
    },
    "희귀 [일품] 장인의 노릇한 꼬치구이": {
        "Id": 6851302,
        "BundleCount": 1
    },
    "희귀 [일품] 달인의 마늘 스테이크": {
        "Id": 6851410,
        "BundleCount": 1
    },
    "희귀 [일품] 달인의 버터 스테이크 정식": {
        "Id": 6851415,
        "BundleCount": 1
    },
    "희귀 [일품] 장인의 매콤한 모둠 스튜": {
        "Id": 6851106,
        "BundleCount": 1
    },
    "희귀 [일품] 달인의 달콤한 스튜": {
        "Id": 6851111,
        "BundleCount": 1
    },
    "희귀 [일품] 명인의 짭짤한 스튜": {
        "Id": 6851120,
        "BundleCount": 1
    },
    "희귀 [일품] 달인의 부드러운 오믈렛": {
        "Id": 6851211,
        "BundleCount": 1
    },
    "희귀 [일품] 장인의 노릇한 양념 꼬치구이": {
        "Id": 6851306,
        "BundleCount": 1
    },
    "희귀 [일품] 달인의 바삭한 꼬치구이": {
        "Id": 6851311,
        "BundleCount": 1
    },
    "희귀 [일품] 달인의 마늘 스테이크 정식": {
        "Id": 6851414,
        "BundleCount": 1
    },
    "희귀 [일품] 달인의 폭신한 전통 오믈렛": {
        "Id": 6851214,
        "BundleCount": 1
    },
    "희귀 [일품] 달인의 달콤한 모둠 스튜": {
        "Id": 6851115,
        "BundleCount": 1
    },
    "희귀 별구름 카프레제 VI": {
        "Id": 821006,
        "BundleCount": 1
    },
    "희귀 [일품] 달인의 부드러운 전통 오믈렛": {
        "Id": 6851215,
        "BundleCount": 1
    },
    "희귀 [일품] 달인의 바삭한 양념 꼬치구이": {
        "Id": 6851315,
        "BundleCount": 1
    },
    "희귀 [일품] 장인의 쫄깃한 꼬치구이": {
        "Id": 6851304,
        "BundleCount": 1
    },
    "희귀 [일품] 명인의 버터 스테이크": {
        "Id": 6851419,
        "BundleCount": 1
    },
    "희귀 [일품] 명인의 부드러운 오믈렛": {
        "Id": 6851219,
        "BundleCount": 1
    },
    "희귀 그릴피쉬 피카타 IV": {
        "Id": 821054,
        "BundleCount": 1
    },
    "희귀 [일품] 달인의 매콤한 스튜": {
        "Id": 6851110,
        "BundleCount": 1
    },
    "희귀 [일품] 달인의 노릇한 꼬치구이": {
        "Id": 6851310,
        "BundleCount": 1
    },
    "희귀 [일품] 달인의 촉촉한 오믈렛": {
        "Id": 6851212,
        "BundleCount": 1
    },
    "희귀 [일품] 달인의 허브 스테이크 정식": {
        "Id": 6851416,
        "BundleCount": 1
    },
    "희귀 [일품] 달인의 매콤한 모둠 스튜": {
        "Id": 6851114,
        "BundleCount": 1
    },
    "희귀 [일품] 장인의 쫄깃한 양념 꼬치구이": {
        "Id": 6851308,
        "BundleCount": 1
    },
    "희귀 [일품] 달인의 노릇한 양념 꼬치구이": {
        "Id": 6851314,
        "BundleCount": 1
    },
    "희귀 [일품] 달인의 허브 스테이크": {
        "Id": 6851412,
        "BundleCount": 1
    },
    "희귀 그릴피쉬 피카타 VI": {
        "Id": 821056,
        "BundleCount": 1
    },
    "희귀 [일품] 장인의 짭짤한 모둠 스튜": {
        "Id": 6851108,
        "BundleCount": 1
    },
    "희귀 [일품] 달인의 쫄깃한 꼬치구이": {
        "Id": 6851312,
        "BundleCount": 1
    },
    "희귀 [일품] 명인의 노릇한 꼬치구이": {
        "Id": 6851318,
        "BundleCount": 1
    },
    "희귀 [일품] 달인의 쫄깃한 양념 꼬치구이": {
        "Id": 6851316,
        "BundleCount": 1
    },
    "희귀 [일품] 달인의 짭짤한 모둠 스튜": {
        "Id": 6851116,
        "BundleCount": 1
    },
    "희귀 [일품] 명인의 촉촉한 오믈렛": {
        "Id": 6851220,
        "BundleCount": 1
    },
    "희귀 [일품] 명인의 허브 스테이크": {
        "Id": 6851420,
        "BundleCount": 1
    },
    "일반 목재 [100개 단위 판매]": {
        "Id": 6882301,
        "BundleCount": 100
    },
    "일반 철광석 [100개 단위 판매]": {
        "Id": 6882401,
        "BundleCount": 100
    },
    "일반 생선 [100개 단위 판매]": {
        "Id": 6882601,
        "BundleCount": 100
    },
    "일반 고대 유물 [100개 단위 판매]": {
        "Id": 6882701,
        "BundleCount": 100
    },
    "일반 들꽃 [100개 단위 판매]": {
        "Id": 6882101,
        "BundleCount": 100
    },
    "일반 두툼한 생고기 [100개 단위 판매]": {
        "Id": 6882501,
        "BundleCount": 100
    },
    "고급 도구 제작 부품": {
        "Id": 6866002,
        "BundleCount": 1
    },
    "고급 초보자용 제작 키트": {
        "Id": 6812001,
        "BundleCount": 1
    },
    "고급 부드러운 목재 [100개 단위 판매]": {
        "Id": 6882304,
        "BundleCount": 100
    },
    "고급 희귀한 유물 [100개 단위 판매]": {
        "Id": 6882704,
        "BundleCount": 100
    },
    "고급 붉은 살 생선 [100개 단위 판매]": {
        "Id": 6882604,
        "BundleCount": 100
    },
    "고급 다듬은 생고기 [100개 단위 판매]": {
        "Id": 6882504,
        "BundleCount": 100
    },
    "고급 묵직한 철광석 [100개 단위 판매]": {
        "Id": 6882404,
        "BundleCount": 100
    },
    "고급 수줍은 들꽃 [100개 단위 판매]": {
        "Id": 6882104,
        "BundleCount": 100
    },
    "희귀 견습생용 제작 키트": {
        "Id": 6812002,
        "BundleCount": 1
    },
    "희귀 진귀한 가죽 [100개 단위 판매]": {
        "Id": 6885505,
        "BundleCount": 100
    },
    "희귀 진귀한 유물 [100개 단위 판매]": {
        "Id": 6885705,
        "BundleCount": 100
    },
    "희귀 화사한 들꽃 [100개 단위 판매]": {
        "Id": 6882107,
        "BundleCount": 100
    },
    "희귀 오레하 두툼한 생고기 [100개 단위 판매]": {
        "Id": 6885508,
        "BundleCount": 100
    },
    "희귀 튼튼한 목재 [100개 단위 판매]": {
        "Id": 6884307,
        "BundleCount": 100
    },
    "희귀 단단한 철광석 [100개 단위 판매]": {
        "Id": 6884407,
        "BundleCount": 100
    },
    "희귀 오레하 태양 잉어 [100개 단위 판매]": {
        "Id": 6885608,
        "BundleCount": 100
    },
    "희귀 오레하 유물 [100개 단위 판매]": {
        "Id": 6885708,
        "BundleCount": 100
    },
    "희귀 아비도스 들꽃 [100개 단위 판매]": {
        "Id": 6882109,
        "BundleCount": 100
    },
    "희귀 아비도스 철광석 [100개 단위 판매]": {
        "Id": 6884408,
        "BundleCount": 100
    },
    "희귀 아비도스 목재 [100개 단위 판매]": {
        "Id": 6884308,
        "BundleCount": 100
    },
    "희귀 아비도스 유물 [100개 단위 판매]": {
        "Id": 6885709,
        "BundleCount": 100
    },
    "희귀 아비도스 태양 잉어 [100개 단위 판매]": {
        "Id": 6885609,
        "BundleCount": 100
    },
    "희귀 아비도스 두툼한 생고기 [100개 단위 판매]": {
        "Id": 6885509,
        "BundleCount": 100
    },
    "영웅 숙련가용 제작 키트": {
        "Id": 6812003,
        "BundleCount": 1
    },
    "영웅 수렵의 결정 [10개 단위 판매]": {
        "Id": 6882508,
        "BundleCount": 10
    },
    "영웅 낚시의 결정 [10개 단위 판매]": {
        "Id": 6882608,
        "BundleCount": 10
    },
    "영웅 고고학의 결정 [10개 단위 판매]": {
        "Id": 6882708,
        "BundleCount": 10
    },
    "전설 전문가용 제작 키트": {
        "Id": 6812004,
        "BundleCount": 1
    },
    "유물 달인용 제작 키트": {
        "Id": 6812005,
        "BundleCount": 1
    },
    "일반 고대 정령 도감": {
        "Id": 909102,
        "BundleCount": 1
    },
    "일반 안개가 담긴 호리병": {
        "Id": 910302,
        "BundleCount": 1
    },
    "일반 니바르의 손": {
        "Id": 907101,
        "BundleCount": 1
    },
    "일반 칼다르의 투구": {
        "Id": 907102,
        "BundleCount": 1
    },
    "일반 떠밀려 온 물병": {
        "Id": 910202,
        "BundleCount": 1
    },
    "일반 시엔 영웅담": {
        "Id": 910301,
        "BundleCount": 1
    },
    "일반 의문의 신호가 적힌 철판": {
        "Id": 910401,
        "BundleCount": 1
    },
    "일반 신성연방의 증표": {
        "Id": 911001,
        "BundleCount": 1
    },
    "일반 독액 묻은 화살": {
        "Id": 911002,
        "BundleCount": 1
    },
    "일반 기사단의 갑옷 조각": {
        "Id": 911101,
        "BundleCount": 1
    },
    "일반 아말론의 일지": {
        "Id": 911102,
        "BundleCount": 1
    },
    "일반 세공된 깃털 보관함": {
        "Id": 911201,
        "BundleCount": 1
    },
    "일반 빛이 깃든 파편": {
        "Id": 911202,
        "BundleCount": 1
    },
    "일반 태양소금": {
        "Id": 911701,
        "BundleCount": 1
    },
    "일반 도적단의 맹세": {
        "Id": 911702,
        "BundleCount": 1
    },
    "일반 잘 익은 두리넛": {
        "Id": 912502,
        "BundleCount": 1
    },
    "일반 부치지 못한 편지": {
        "Id": 909101,
        "BundleCount": 1
    },
    "일반 루페온 신상 조각": {
        "Id": 910101,
        "BundleCount": 1
    },
    "일반 역병 포자": {
        "Id": 910102,
        "BundleCount": 1
    },
    "일반 하이비 꿀": {
        "Id": 910201,
        "BundleCount": 1
    },
    "일반 마리의 기계인형": {
        "Id": 910402,
        "BundleCount": 1
    },
    "일반 얼음나비": {
        "Id": 910601,
        "BundleCount": 1
    },
    "일반 여명의 목소리": {
        "Id": 910602,
        "BundleCount": 1
    },
    "일반 실리안 수배 전단": {
        "Id": 911401,
        "BundleCount": 1
    },
    "일반 백인대장의 수첩": {
        "Id": 911402,
        "BundleCount": 1
    },
    "일반 독수리 반지": {
        "Id": 911501,
        "BundleCount": 1
    },
    "일반 로나운의 열쇠": {
        "Id": 911502,
        "BundleCount": 1
    },
    "일반 귀미테 패치": {
        "Id": 912501,
        "BundleCount": 1
    },
    "일반 파푸니카 특산품 일람": {
        "Id": 910802,
        "BundleCount": 1
    },
    "일반 모구로 가면": {
        "Id": 910801,
        "BundleCount": 1
    },
    "일반 영혼을 부르는 목판": {
        "Id": 911902,
        "BundleCount": 1
    },
    "일반 취직 알선 벽보": {
        "Id": 911901,
        "BundleCount": 1
    },
    "일반 걱정 인형": {
        "Id": 912601,
        "BundleCount": 1
    },
    "일반 망가진 무전기": {
        "Id": 912602,
        "BundleCount": 1
    },
    "일반 쿠르잔 생존 교범": {
        "Id": 911302,
        "BundleCount": 1
    },
    "일반 타이예르의 부적": {
        "Id": 912402,
        "BundleCount": 1
    },
    "일반 엘리야베크 문양": {
        "Id": 912401,
        "BundleCount": 1
    },
    "일반 빛을 잃은 혼돈의 결정 파편": {
        "Id": 911301,
        "BundleCount": 1
    },
    "고급 발레르의 연시": {
        "Id": 907104,
        "BundleCount": 1
    },
    "고급 토토이크의 기원": {
        "Id": 910203,
        "BundleCount": 1
    },
    "고급 현상금 수배지": {
        "Id": 910204,
        "BundleCount": 1
    },
    "고급 경계의 고서": {
        "Id": 910304,
        "BundleCount": 1
    },
    "고급 얼음거미 고치": {
        "Id": 910603,
        "BundleCount": 1
    },
    "고급 바에단의 금화": {
        "Id": 910604,
        "BundleCount": 1
    },
    "고급 아베스타 수기": {
        "Id": 911003,
        "BundleCount": 1
    },
    "고급 두꺼운 양피지": {
        "Id": 911104,
        "BundleCount": 1
    },
    "고급 찢어진 세이크리아 깃발": {
        "Id": 912603,
        "BundleCount": 1
    },
    "고급 냄새 나는 장화": {
        "Id": 907103,
        "BundleCount": 1
    },
    "고급 예언가의 노트": {
        "Id": 909104,
        "BundleCount": 1
    },
    "고급 애니츠 요리책": {
        "Id": 910303,
        "BundleCount": 1
    },
    "고급 아베스타의 붉은 천": {
        "Id": 911004,
        "BundleCount": 1
    },
    "고급 사피라 연구일지": {
        "Id": 911703,
        "BundleCount": 1
    },
    "고급 라멜라의 거울": {
        "Id": 911704,
        "BundleCount": 1
    },
    "고급 엘조윈의 나뭇가지": {
        "Id": 909103,
        "BundleCount": 1
    },
    "고급 신관의 서": {
        "Id": 910103,
        "BundleCount": 1
    },
    "고급 그랑고르의 이빨": {
        "Id": 910104,
        "BundleCount": 1
    },
    "고급 크라테르의 성서": {
        "Id": 910403,
        "BundleCount": 1
    },
    "고급 노이호이테 일보": {
        "Id": 910404,
        "BundleCount": 1
    },
    "고급 가디언의 기록": {
        "Id": 911103,
        "BundleCount": 1
    },
    "고급 향수 미스 기에나": {
        "Id": 911203,
        "BundleCount": 1
    },
    "고급 베스페르 용과": {
        "Id": 911303,
        "BundleCount": 1
    },
    "고급 망자의 금화": {
        "Id": 911503,
        "BundleCount": 1
    },
    "고급 루오덴 강의 전설": {
        "Id": 911504,
        "BundleCount": 1
    },
    "고급 문어발 은화": {
        "Id": 912403,
        "BundleCount": 1
    },
    "고급 현자와 가디언 카드팩": {
        "Id": 912503,
        "BundleCount": 1
    },
    "고급 붉은손 용병단의 장갑": {
        "Id": 911403,
        "BundleCount": 1
    },
    "고급 몰락한 귀족의 펜던트": {
        "Id": 911404,
        "BundleCount": 1
    },
    "고급 별빛 소라 껍데기": {
        "Id": 910803,
        "BundleCount": 1
    },
    "고급 소원등": {
        "Id": 910804,
        "BundleCount": 1
    },
    "고급 악몽의 비약": {
        "Id": 911903,
        "BundleCount": 1
    },
    "희귀 천공의 구슬": {
        "Id": 911204,
        "BundleCount": 1
    },
    "희귀 악마의 북": {
        "Id": 912604,
        "BundleCount": 1
    },
    "희귀 말라비틀어진 악마손": {
        "Id": 911304,
        "BundleCount": 1
    },
    "희귀 아주 작은 뱅글루스": {
        "Id": 912504,
        "BundleCount": 1
    },
    "희귀 수염가발": {
        "Id": 907105,
        "BundleCount": 1
    },
    "희귀 일간지 전설의 주당": {
        "Id": 907106,
        "BundleCount": 1
    },
    "희귀 그믐의 마법서": {
        "Id": 912404,
        "BundleCount": 1
    },
    "희귀 화려한 찻잔 받침": {
        "Id": 911904,
        "BundleCount": 1
    },
    "희귀 타락한 자의 선혈": {
        "Id": 911006,
        "BundleCount": 1
    },
    "희귀 할 유적 연구 일지": {
        "Id": 910805,
        "BundleCount": 1
    },
    "희귀 헤비워커 보고서": {
        "Id": 910405,
        "BundleCount": 1
    },
    "희귀 에어가이츠 홍보지": {
        "Id": 910406,
        "BundleCount": 1
    },
    "희귀 루테란 기사 열전": {
        "Id": 911506,
        "BundleCount": 1
    },
    "희귀 제사장의 단검": {
        "Id": 911505,
        "BundleCount": 1
    },
    "희귀 왕실 경고문": {
        "Id": 911106,
        "BundleCount": 1
    },
    "희귀 모험가의 일지": {
        "Id": 911105,
        "BundleCount": 1
    },
    "희귀 니아족 꿈장식": {
        "Id": 910806,
        "BundleCount": 1
    },
    "희귀 차원의 돌": {
        "Id": 910105,
        "BundleCount": 1
    },
    "희귀 레바타노스 핵": {
        "Id": 911705,
        "BundleCount": 1
    },
    "희귀 요괴 가면": {
        "Id": 910306,
        "BundleCount": 1
    },
    "희귀 소금나무 열매": {
        "Id": 911706,
        "BundleCount": 1
    },
    "희귀 항아의 봉인부": {
        "Id": 910305,
        "BundleCount": 1
    },
    "희귀 아길로스의 허물": {
        "Id": 910106,
        "BundleCount": 1
    },
    "희귀 낡아빠진 투사의 칼": {
        "Id": 910606,
        "BundleCount": 1
    },
    "희귀 여기사의 목각인형": {
        "Id": 911406,
        "BundleCount": 1
    },
    "희귀 루테란 대왕의 전설": {
        "Id": 911405,
        "BundleCount": 1
    },
    "희귀 아드린느의 반지": {
        "Id": 909105,
        "BundleCount": 1
    },
    "희귀 엔비스카의 부적": {
        "Id": 909106,
        "BundleCount": 1
    },
    "희귀 비밀 장부": {
        "Id": 910605,
        "BundleCount": 1
    },
    "희귀 까마귀 돌": {
        "Id": 911005,
        "BundleCount": 1
    },
    "희귀 문양이 새겨진 돌": {
        "Id": 910206,
        "BundleCount": 1
    },
    "희귀 악취 나는 비늘": {
        "Id": 910205,
        "BundleCount": 1
    },
    "영웅 병에 담긴 모래": {
        "Id": 910407,
        "BundleCount": 1
    },
    "영웅 검은 이리 깃발": {
        "Id": 911507,
        "BundleCount": 1
    },
    "영웅 캐슈 열매": {
        "Id": 910207,
        "BundleCount": 1
    },
    "영웅 거대한 꽃잎": {
        "Id": 910307,
        "BundleCount": 1
    },
    "영웅 음유시인의 악보": {
        "Id": 911205,
        "BundleCount": 1
    },
    "영웅 별의 나침반": {
        "Id": 911206,
        "BundleCount": 1
    },
    "영웅 새벽의 회중시계": {
        "Id": 909107,
        "BundleCount": 1
    },
    "영웅 피 묻은 지팡이": {
        "Id": 910107,
        "BundleCount": 1
    },
    "영웅 암호가 적힌 종이": {
        "Id": 911107,
        "BundleCount": 1
    },
    "영웅 라카이서스의 혈흔 조각": {
        "Id": 910607,
        "BundleCount": 1
    },
    "영웅 린지스의 반지": {
        "Id": 911407,
        "BundleCount": 1
    },
    "영웅 아베스타 명단": {
        "Id": 911007,
        "BundleCount": 1
    },
    "영웅 아덴토의 연구 일지": {
        "Id": 912505,
        "BundleCount": 1
    },
    "영웅 불에 탄 기념주화": {
        "Id": 912506,
        "BundleCount": 1
    },
    "영웅 멜레마르의 어금니": {
        "Id": 912405,
        "BundleCount": 1
    },
    "영웅 노래가 새겨진 돌": {
        "Id": 910807,
        "BundleCount": 1
    },
    "영웅 두억시니 돌": {
        "Id": 912406,
        "BundleCount": 1
    },
    "영웅 태양의 돌": {
        "Id": 911905,
        "BundleCount": 1
    },
    "영웅 태양의 기사단 징표": {
        "Id": 911906,
        "BundleCount": 1
    },
    "영웅 유랑민의 꿈": {
        "Id": 911707,
        "BundleCount": 1
    },
    "영웅 병에 담긴 불길한 안개": {
        "Id": 912606,
        "BundleCount": 1
    },
    "영웅 전함 플루토 모형": {
        "Id": 912605,
        "BundleCount": 1
    },
    "영웅 점술 판각": {
        "Id": 911306,
        "BundleCount": 1
    },
    "영웅 빛바랜 성배": {
        "Id": 911305,
        "BundleCount": 1
    },
    "영웅 갈라투르 전기": {
        "Id": 907107,
        "BundleCount": 1
    },
    "전설 구겨진 편지": {
        "Id": 911907,
        "BundleCount": 1
    },
    "전설 다면체 조각": {
        "Id": 912607,
        "BundleCount": 1
    },
    "전설 오래된 유적 파편": {
        "Id": 911307,
        "BundleCount": 1
    },
    "전설 마지막 숨을 담은 통": {
        "Id": 912407,
        "BundleCount": 1
    },
    "전설 현자의 매듭": {
        "Id": 912507,
        "BundleCount": 1
    },
    "전설 프로키온의 숨결": {
        "Id": 911207,
        "BundleCount": 1
    },
    "일반 일반 선박 부품 재료": {
        "Id": 6862001,
        "BundleCount": 1
    },
    "고급 고급 선박 부품 재료": {
        "Id": 6862002,
        "BundleCount": 1
    },
    "희귀 희귀 선박 부품 재료": {
        "Id": 6862003,
        "BundleCount": 1
    },
    "영웅 영웅 선박 부품 재료": {
        "Id": 6862004,
        "BundleCount": 1
    },
    "영웅 선박스킨 : 잭 오 랜턴의 유랑": {
        "Id": 721015,
        "BundleCount": 1
    },
    "영웅 선박스킨 : 노스페라투": {
        "Id": 721014,
        "BundleCount": 1
    },
    "영웅 불가사리 펫 선택 상자": {
        "Id": 40112297,
        "BundleCount": 1
    },
    "영웅 펫 : 절미": {
        "Id": 151703,
        "BundleCount": 1
    },
    "영웅 펫 : 보리": {
        "Id": 151700,
        "BundleCount": 1
    },
    "영웅 펫 : 양갱": {
        "Id": 151704,
        "BundleCount": 1
    },
    "영웅 펫 : 두부": {
        "Id": 151702,
        "BundleCount": 1
    },
    "영웅 펫 : 먼지": {
        "Id": 151701,
        "BundleCount": 1
    },
    "영웅 가오리 펫 선택 상자": {
        "Id": 61900097,
        "BundleCount": 1
    },
    "영웅 펫 : 살살가오": {
        "Id": 156004,
        "BundleCount": 1
    },
    "영웅 펫 : 죠리가오": {
        "Id": 156003,
        "BundleCount": 1
    },
    "영웅 시바견 펫 선택 상자": {
        "Id": 40112091,
        "BundleCount": 1
    },
    "영웅 용 펫 선택 상자": {
        "Id": 61900057,
        "BundleCount": 1
    },
    "영웅 펫 : 요리가오": {
        "Id": 156002,
        "BundleCount": 1
    },
    "영웅 펫 : 저리가오": {
        "Id": 156001,
        "BundleCount": 1
    },
    "영웅 펫 : 이리가오": {
        "Id": 156000,
        "BundleCount": 1
    },
    "영웅 펫 : 바다별 핑키": {
        "Id": 152100,
        "BundleCount": 1
    },
    "영웅 펫 : 바다별 할라": {
        "Id": 152103,
        "BundleCount": 1
    },
    "영웅 펫 : 바다별 동구": {
        "Id": 152101,
        "BundleCount": 1
    },
    "영웅 펫 : 바다별 아치": {
        "Id": 152102,
        "BundleCount": 1
    },
    "영웅 펫 : 바다별 후크": {
        "Id": 152104,
        "BundleCount": 1
    },
    "영웅 펫 : 으쓱한 토토": {
        "Id": 152306,
        "BundleCount": 1
    },
    "영웅 호두까기 인형 선택 상자": {
        "Id": 61000001,
        "BundleCount": 1
    },
    "영웅 강아지 펫 선택 상자": {
        "Id": 40113800,
        "BundleCount": 1
    },
    "영웅 펫 : 찬란한 백룡": {
        "Id": 155202,
        "BundleCount": 1
    },
    "영웅 펫 : 행복한 청룡": {
        "Id": 155200,
        "BundleCount": 1
    },
    "영웅 펫 : 하얀마음 토토": {
        "Id": 152300,
        "BundleCount": 1
    },
    "영웅 펫 : 새침한 토토": {
        "Id": 152303,
        "BundleCount": 1
    },
    "영웅 펫 : 긴장한 모카": {
        "Id": 152307,
        "BundleCount": 1
    },
    "영웅 펫 : 미하일 ": {
        "Id": 152502,
        "BundleCount": 1
    },
    "영웅 펫 : 뾰로통한 초코": {
        "Id": 152302,
        "BundleCount": 1
    },
    "영웅 펫 : 당당한 초코": {
        "Id": 152305,
        "BundleCount": 1
    },
    "영웅 개구리 펫 선택 상자": {
        "Id": 61000399,
        "BundleCount": 1
    },
    "영웅 펫 : 알렉세이": {
        "Id": 152500,
        "BundleCount": 1
    },
    "영웅 펫 : 예브게니": {
        "Id": 152501,
        "BundleCount": 1
    },
    "영웅 크리스마스 물범 펫 선택 상자": {
        "Id": 61900007,
        "BundleCount": 1
    },
    "영웅 슬라임 펫 선택 상자": {
        "Id": 61900223,
        "BundleCount": 1
    },
    "영웅 로보 펫 선택 상자": {
        "Id": 61900102,
        "BundleCount": 1
    },
    "영웅 6주년 펫 선택 상자": {
        "Id": 61900254,
        "BundleCount": 1
    },
    "영웅 펫 : 토토앙쥬": {
        "Id": 150011,
        "BundleCount": 1
    },
    "영웅 펫 : 몰캉한 민트룽": {
        "Id": 156300,
        "BundleCount": 1
    },
    "영웅 펫 : 몽실몽실 도스터": {
        "Id": 156401,
        "BundleCount": 1
    },
    "영웅 펫 : 통실통실 도스터": {
        "Id": 156403,
        "BundleCount": 1
    },
    "영웅 밤 고양이 선택 상자": {
        "Id": 61000525,
        "BundleCount": 1
    },
    "영웅 펫 : 몰랑몰랑 도스터": {
        "Id": 156400,
        "BundleCount": 1
    },
    "영웅 펫 : 몽글몽글 도스터": {
        "Id": 156404,
        "BundleCount": 1
    },
    "영웅 펫 : 말랑말랑 도스터": {
        "Id": 156402,
        "BundleCount": 1
    },
    "영웅 펫 : 개구진 할로윙": {
        "Id": 156304,
        "BundleCount": 1
    },
    "영웅 해달 선택 상자": {
        "Id": 61001087,
        "BundleCount": 1
    },
    "영웅 펫 : 깐깐한 다비룽": {
        "Id": 156301,
        "BundleCount": 1
    },
    "영웅 펫 : 곱게 단장한 호키": {
        "Id": 153306,
        "BundleCount": 1
    },
    "영웅 펫 : 하얀 마음 버미": {
        "Id": 154700,
        "BundleCount": 1
    },
    "영웅 펫 : 단호한 프랑소와즈": {
        "Id": 151052,
        "BundleCount": 1
    },
    "영웅 펫 : 토토악마 선택 상자": {
        "Id": 40110240,
        "BundleCount": 1
    },
    "영웅 키스 펫 선택 상자": {
        "Id": 61000627,
        "BundleCount": 1
    },
    "영웅 펫 : 유자 망토 애옹이": {
        "Id": 152802,
        "BundleCount": 1
    },
    "영웅 펫 : 강인한 세바스찬": {
        "Id": 155504,
        "BundleCount": 1
    },
    "영웅 쁘띠세이튼 선택 상자": {
        "Id": 40113924,
        "BundleCount": 1
    },
    "영웅 펫 : 터프한 루비룽": {
        "Id": 156302,
        "BundleCount": 1
    },
    "영웅 몽마 펫 선택 상자": {
        "Id": 61001233,
        "BundleCount": 1
    },
    "영웅 펫 : 새벽을 여는 냐옹이": {
        "Id": 152803,
        "BundleCount": 1
    },
    "영웅 펫 : 뽀송한 호키": {
        "Id": 153300,
        "BundleCount": 1
    },
    "영웅 해골 펫 선택 상자": {
        "Id": 61900080,
        "BundleCount": 1
    },
    "영웅 펫 : 흑화한 쿠큐": {
        "Id": 152401,
        "BundleCount": 1
    },
    "영웅 펫 : 델피나": {
        "Id": 151901,
        "BundleCount": 1
    },
    "영웅 펫 : 메이릴리": {
        "Id": 151904,
        "BundleCount": 1
    },
    "영웅 펫 : 카멜리아": {
        "Id": 151905,
        "BundleCount": 1
    },
    "영웅 펫 : 지니아": {
        "Id": 152005,
        "BundleCount": 1
    },
    "영웅 펫 : 피오니": {
        "Id": 151900,
        "BundleCount": 1
    },
    "영웅 펫 : 코스모": {
        "Id": 152003,
        "BundleCount": 1
    },
    "영웅 펫 : 네로": {
        "Id": 152201,
        "BundleCount": 1
    },
    "영웅 왕관 고양이 펫 선택 상자": {
        "Id": 61001036,
        "BundleCount": 1
    },
    "영웅 표범 펫 선택 상자": {
        "Id": 40112111,
        "BundleCount": 1
    },
    "영웅 펫 : 클로버": {
        "Id": 152002,
        "BundleCount": 1
    },
    "영웅 펫 : 달콤한 키스": {
        "Id": 153100,
        "BundleCount": 1
    },
    "영웅 펫 : 오키드": {
        "Id": 152004,
        "BundleCount": 1
    },
    "영웅 펫 : 라피스": {
        "Id": 152000,
        "BundleCount": 1
    },
    "영웅 펫 : 아련한 키스": {
        "Id": 153103,
        "BundleCount": 1
    },
    "영웅 펫 : 눈부신 키스": {
        "Id": 153102,
        "BundleCount": 1
    },
    "영웅 펫 : 밤의 무법자 아옹이": {
        "Id": 152800,
        "BundleCount": 1
    },
    "영웅 펫 : 앵보니": {
        "Id": 151303,
        "BundleCount": 1
    },
    "영웅 펫 : 볼다이크 레오파드": {
        "Id": 151101,
        "BundleCount": 1
    },
    "영웅 펫 랜덤 상자": {
        "Id": 40111273,
        "BundleCount": 1
    },
    "영웅 펫 : 차가운 키스": {
        "Id": 153101,
        "BundleCount": 1
    },
    "영웅 펫 : 음흉한 쿠캬": {
        "Id": 152400,
        "BundleCount": 1
    },
    "영웅 펫 : 슈샤이어 설표": {
        "Id": 151102,
        "BundleCount": 1
    },
    "영웅 새해 토끼 선택 상자": {
        "Id": 61000834,
        "BundleCount": 1
    },
    "영웅 토끼 기사 펫 선택 상자": {
        "Id": 61900024,
        "BundleCount": 1
    },
    "영웅 5주년 펫 선택 상자": {
        "Id": 61001280,
        "BundleCount": 1
    },
    "영웅 펫 : 보송한 달여우": {
        "Id": 154503,
        "BundleCount": 1
    },
    "영웅 펫 : 덤덤한 제임스": {
        "Id": 155500,
        "BundleCount": 1
    },
    "영웅 펫 : 포근한 달여우": {
        "Id": 154504,
        "BundleCount": 1
    },
    "영웅 크로마롱 선택 상자": {
        "Id": 40100361,
        "BundleCount": 1
    },
    "영웅 펫 : 헬가핌": {
        "Id": 151010,
        "BundleCount": 1
    },
    "영웅 해적 앵무새 펫 선택 상자": {
        "Id": 40111240,
        "BundleCount": 1
    },
    "영웅 펫 : 도토리 망토 슈피": {
        "Id": 151504,
        "BundleCount": 1
    },
    "영웅 펫 : 햇살반 보들이": {
        "Id": 152903,
        "BundleCount": 1
    },
    "영웅 모코코 유치원 강아지 선택 상자": {
        "Id": 61000753,
        "BundleCount": 1
    },
    "영웅 할로윈 펫 선택 상자": {
        "Id": 216449,
        "BundleCount": 1
    },
    "영웅 펫 : 앵르바로사": {
        "Id": 151304,
        "BundleCount": 1
    },
    "영웅 꼬마 유령 선택 상자": {
        "Id": 40111330,
        "BundleCount": 1
    },
    "영웅 아기 소 펫 선택 상자": {
        "Id": 40112002,
        "BundleCount": 1
    },
    "영웅 망토 여우 펫 선택 상자": {
        "Id": 40111809,
        "BundleCount": 1
    },
    "영웅 펫 : 포이코이": {
        "Id": 151405,
        "BundleCount": 1
    },
    "영웅 펫 : 포이포이": {
        "Id": 151400,
        "BundleCount": 1
    },
    "영웅 펫 : 포도 망토 슈나": {
        "Id": 151503,
        "BundleCount": 1
    },
    "영웅 펫 : 당근 망토 슈리": {
        "Id": 151502,
        "BundleCount": 1
    },
    "영웅 펫 : 수줍은 아카테냥": {
        "Id": 151022,
        "BundleCount": 1
    },
    "영웅 펫 : 포이뮤이": {
        "Id": 151403,
        "BundleCount": 1
    },
    "영웅 펫 : 포이아이": {
        "Id": 151404,
        "BundleCount": 1
    },
    "영웅 펫 : 포이호이": {
        "Id": 151401,
        "BundleCount": 1
    },
    "영웅 펫 : 도도한 아카테냥": {
        "Id": 151021,
        "BundleCount": 1
    },
    "영웅 2019 여름 펫 선택 상자": {
        "Id": 216251,
        "BundleCount": 1
    },
    "영웅 크리스마스 펫 선택 상자": {
        "Id": 40100039,
        "BundleCount": 1
    },
    "영웅 펫 : 금의 요호링": {
        "Id": 151043,
        "BundleCount": 1
    },
    "영웅 탈것 : 길들인 붉은 야생 늑대": {
        "Id": 128052,
        "BundleCount": 1
    },
    "영웅 탈것 : 근두운": {
        "Id": 128073,
        "BundleCount": 1
    },
    "영웅 마법 침대 탈것 선택 상자": {
        "Id": 61000002,
        "BundleCount": 1
    },
    "영웅 2019 여름 탈것 선택 상자": {
        "Id": 216241,
        "BundleCount": 1
    },
    "영웅 슈타이페 브리제 선택 상자": {
        "Id": 216151,
        "BundleCount": 1
    },
    "영웅 스노우 바이크 선택 상자": {
        "Id": 40100038,
        "BundleCount": 1
    },
    "영웅 호박마차 선택 상자": {
        "Id": 216448,
        "BundleCount": 1
    },
    "전설 갑주 마차 선택 상자": {
        "Id": 40112296,
        "BundleCount": 1
    },
    "전설 탈것 : 루비 갑주 마차": {
        "Id": 127113,
        "BundleCount": 1
    },
    "전설 탈것 : 오닉스 갑주 마차": {
        "Id": 127115,
        "BundleCount": 1
    },
    "전설 탈것 : 오팔 갑주 마차": {
        "Id": 127114,
        "BundleCount": 1
    },
    "전설 탈것 : 산호 갑주 마차": {
        "Id": 127112,
        "BundleCount": 1
    },
    "전설 스윙 라이드 탈것 선택 상자": {
        "Id": 61900096,
        "BundleCount": 1
    },
    "전설 탈것 : 태양 스윙 라이드": {
        "Id": 127235,
        "BundleCount": 1
    },
    "전설 탈것 : 노을 스윙 라이드": {
        "Id": 127236,
        "BundleCount": 1
    },
    "전설 탈것 : 바다 스윙 라이드": {
        "Id": 127233,
        "BundleCount": 1
    },
    "전설 탈것 : 해변 스윙 라이드": {
        "Id": 127232,
        "BundleCount": 1
    },
    "전설 탈것 : 여름 스윙 라이드": {
        "Id": 127234,
        "BundleCount": 1
    },
    "전설 윈드서핑 세트 선택 상자": {
        "Id": 61000400,
        "BundleCount": 1
    },
    "전설 탈것 : 윈드서핑 세트 W": {
        "Id": 127150,
        "BundleCount": 1
    },
    "전설 탈것 : 윈드서핑 세트 Y": {
        "Id": 127147,
        "BundleCount": 1
    },
    "전설 탈것 : 윈드서핑 세트 S": {
        "Id": 127148,
        "BundleCount": 1
    },
    "전설 탈것 : 늪의 케르베로스": {
        "Id": 127120,
        "BundleCount": 1
    },
    "전설 탈것 : 화산의 케르베로스": {
        "Id": 127123,
        "BundleCount": 1
    },
    "전설 바이크 탈것 선택 상자": {
        "Id": 40113308,
        "BundleCount": 1
    },
    "전설 탈것 : 글라이드 O 바이크": {
        "Id": 127101,
        "BundleCount": 1
    },
    "전설 탈것 : 글라이드 G 바이크": {
        "Id": 127102,
        "BundleCount": 1
    },
    "전설 탈것 : 빙하의 케르베로스": {
        "Id": 127117,
        "BundleCount": 1
    },
    "전설 탈것 : 뇌전의 화신": {
        "Id": 127158,
        "BundleCount": 1
    },
    "전설 탈것 : 글라이드 B 바이크": {
        "Id": 127098,
        "BundleCount": 1
    },
    "전설 탈것 : 글라이드 W 바이크": {
        "Id": 127099,
        "BundleCount": 1
    },
    "전설 피냐타 탈것 선택 상자": {
        "Id": 40112181,
        "BundleCount": 1
    },
    "전설 탈것 : 질서의 화신": {
        "Id": 127159,
        "BundleCount": 1
    },
    "전설 케르베로스 탈것 선택 상자": {
        "Id": 61001035,
        "BundleCount": 1
    },
    "전설 탈것 : 호수의 케르베로스": {
        "Id": 127119,
        "BundleCount": 1
    },
    "전설 탈것 : 심해의 케르베로스": {
        "Id": 127122,
        "BundleCount": 1
    },
    "전설 유령마 선택 상자": {
        "Id": 40100200,
        "BundleCount": 1
    },
    "전설 탈것 : 혹한의 화신": {
        "Id": 127157,
        "BundleCount": 1
    },
    "전설 탈것 : 수묵 청룡": {
        "Id": 127210,
        "BundleCount": 1
    },
    "전설 6주년 탈것 선택 상자": {
        "Id": 61900253,
        "BundleCount": 1
    },
    "전설 탈것 : 죄악의 유령마": {
        "Id": 127055,
        "BundleCount": 1
    },
    "전설 탈것 : 수묵 화룡": {
        "Id": 127212,
        "BundleCount": 1
    },
    "전설 탈것 : 혼돈의 유령마": {
        "Id": 127051,
        "BundleCount": 1
    },
    "전설 탈것 : 수묵 황룡": {
        "Id": 127209,
        "BundleCount": 1
    },
    "전설 탈것 : 수묵 백룡": {
        "Id": 127211,
        "BundleCount": 1
    },
    "전설 봉인된 화신 탈것 선택 상자": {
        "Id": 61000626,
        "BundleCount": 1
    },
    "전설 수묵 용 탈 것 선택 상자": {
        "Id": 61900056,
        "BundleCount": 1
    },
    "전설 비트 노움 탈것 선택 상자": {
        "Id": 61900006,
        "BundleCount": 1
    },
    "전설 탈것 : 찬란한 별빛의 가호": {
        "Id": 127249,
        "BundleCount": 1
    },
    "전설 탈것 : 평온한 별빛의 가호": {
        "Id": 127251,
        "BundleCount": 1
    },
    "전설 장미의 왕좌 선택 상자": {
        "Id": 61000524,
        "BundleCount": 1
    },
    "전설 탈것 : 고요한 별빛의 가호": {
        "Id": 127248,
        "BundleCount": 1
    },
    "전설 탈것 : 온화한 별빛의 가호": {
        "Id": 127252,
        "BundleCount": 1
    },
    "전설 탈것 : 영롱한 별빛의 가호": {
        "Id": 127250,
        "BundleCount": 1
    },
    "전설 탈것 : 고귀한 장미의 왕좌": {
        "Id": 127155,
        "BundleCount": 1
    },
    "전설 탈것 : 비트 노움 - G": {
        "Id": 127199,
        "BundleCount": 1
    },
    "전설 탈것 : 비트 노움 - W": {
        "Id": 127201,
        "BundleCount": 1
    },
    "전설 시간의 요람 탈것 선택 상자": {
        "Id": 61900101,
        "BundleCount": 1
    },
    "전설 탈것 : 분노의 유령마": {
        "Id": 127053,
        "BundleCount": 1
    },
    "전설 탈것 : 타락의 유령마": {
        "Id": 127054,
        "BundleCount": 1
    },
    "전설 탈것 : 순수한 장미의 왕좌": {
        "Id": 127152,
        "BundleCount": 1
    },
    "전설 VROOM 스쿠터 탈것 선택 상자": {
        "Id": 61900222,
        "BundleCount": 1
    },
    "전설 5주년 탈것 선택 상자": {
        "Id": 61001279,
        "BundleCount": 1
    },
    "전설 탈것 : 분노한 장미의 왕좌": {
        "Id": 127151,
        "BundleCount": 1
    },
    "전설 탈것 : 지혜로운 시간의 요람": {
        "Id": 127239,
        "BundleCount": 1
    },
    "전설 탈것 : 번쩍거리는 먹빛 구름": {
        "Id": 127022,
        "BundleCount": 1
    },
    "전설 탈것 : 꿈꾸는 시간의 요람": {
        "Id": 127241,
        "BundleCount": 1
    },
    "전설 탈것 : 축복받은 시간의 요람": {
        "Id": 127237,
        "BundleCount": 1
    },
    "전설 탈것 : VROOM-003": {
        "Id": 127257,
        "BundleCount": 1
    },
    "전설 전투 사자 탈것 선택 상자": {
        "Id": 61900078,
        "BundleCount": 1
    },
    "전설 탈것 : 승리의 달달이": {
        "Id": 127191,
        "BundleCount": 1
    },
    "전설 탈것 : 행복의 달달이": {
        "Id": 127192,
        "BundleCount": 1
    },
    "전설 탈것 : 어린이 오리 튜브": {
        "Id": 127186,
        "BundleCount": 1
    },
    "전설 오리 튜브 선택 상자": {
        "Id": 61001086,
        "BundleCount": 1
    },
    "전설 탈것 : 잔영의 전투 사자": {
        "Id": 127220,
        "BundleCount": 1
    },
    "전설 탈것 : 암영의 전투 사자": {
        "Id": 127217,
        "BundleCount": 1
    },
    "전설 탈것 : 환영의 전투 사자": {
        "Id": 127216,
        "BundleCount": 1
    },
    "전설 탈것 : 마린 오리 튜브": {
        "Id": 127187,
        "BundleCount": 1
    },
    "전설 탈것 : 푸르른 꿈결 침대": {
        "Id": 127135,
        "BundleCount": 1
    },
    "전설 탈것 : 차가운 눈빛 구름": {
        "Id": 127023,
        "BundleCount": 1
    },
    "전설 보석 랩터 선택 상자": {
        "Id": 61900023,
        "BundleCount": 1
    },
    "전설 탈것 : 기억의 꿈결 침대": {
        "Id": 127139,
        "BundleCount": 1
    },
    "전설 탈것 : 동심의 꿈결 침대": {
        "Id": 127136,
        "BundleCount": 1
    },
    "전설 탈것 : 새하얀 꿈결 침대": {
        "Id": 127137,
        "BundleCount": 1
    },
    "전설 탈것 : 카우보이 오리 튜브": {
        "Id": 127189,
        "BundleCount": 1
    },
    "전설 눈덩이 탈것 선택 상자": {
        "Id": 40111808,
        "BundleCount": 1
    },
    "전설 탈것 : 베른 엘크": {
        "Id": 128039,
        "BundleCount": 1
    },
    "전설 탈것 : 슈타이페 브리제 - G": {
        "Id": 127027,
        "BundleCount": 1
    },
    "전설 탈것 : 슈타이페 브리제 - Y": {
        "Id": 127025,
        "BundleCount": 1
    },
    "전설 탈것 : 아우프슈텐 - Y": {
        "Id": 127041,
        "BundleCount": 1
    },
    "전설 탈것 : 가이츠 로더 - R": {
        "Id": 127126,
        "BundleCount": 1
    },
    "전설 탈것 : 아우프슈텐 - B": {
        "Id": 127042,
        "BundleCount": 1
    },
    "전설 가이츠 로더 선택 상자": {
        "Id": 40113923,
        "BundleCount": 1
    },
    "전설 탈것 : 아우프슈텐 - G": {
        "Id": 127038,
        "BundleCount": 1
    },
    "전설 탈것 : 슈타이페 브리제 - B": {
        "Id": 127026,
        "BundleCount": 1
    },
    "전설 탈것 : 슈타이페 브리제 - R": {
        "Id": 127028,
        "BundleCount": 1
    },
    "전설 탈것 : 아우프슈텐 - S": {
        "Id": 127043,
        "BundleCount": 1
    },
    "전설 유니콘 튜브 선택 상자": {
        "Id": 40100360,
        "BundleCount": 1
    },
    "전설 호랑이 탈것 선택 상자": {
        "Id": 40112001,
        "BundleCount": 1
    },
    "전설 탈것 : 디오리카 군마": {
        "Id": 128032,
        "BundleCount": 1
    },
    "일반 혼돈의 조각 [10개 단위 판매]": {
        "Id": 120601,
        "BundleCount": 10
    },
    "희귀 T3 보석 상자 (1~3Lv)": {
        "Id": 40110260,
        "BundleCount": 1
    }
}